README.rst
setup.py
flask_pony/__init__.py
flask_pony.egg-info/PKG-INFO
flask_pony.egg-info/SOURCES.txt
flask_pony.egg-info/dependency_links.txt
flask_pony.egg-info/not-zip-safe
flask_pony.egg-info/requires.txt
flask_pony.egg-info/top_level.txt