Metadata-Version: 1.1
Name: flask-pony
Version: 3.0.1
Summary: PonyORM for your Flask application
Home-page: https://github.com/kyzima-spb/flask-pony
Author: Kirill Vercetti
Author-email: office@kyzima-spb.com
License: Apache-2.0
Platform: any
Classifier: Development Status :: 4 - Beta
Classifier: Environment :: Web Environment
Classifier: Intended Audience :: Developers
Classifier: Operating System :: OS Independent
Classifier: Programming Language :: Python
Classifier: Topic :: Internet :: WWW/HTTP :: Dynamic Content
Classifier: Topic :: Software Development :: Libraries :: Python Modules
